{"fin_helmi":{"team":"","boat_info":{"source":"orc","name":"Helmi","class":"OCEANIS 323","age":"2004","builder":"BENETEAU","designer":"FINOT"},"boat_base_spec":{"source":"orc","dimension":{"length_over_all":9.75,"draft":1.821,"beam":3.252,"forestay_height":8.705,"wetted_surface_area":21.86,"displacement":4851,"crew_weight":500},"sail_area":{"main":30.49,"jib":22.7,"asymmetric_spinnaker":0,"symmetric_spinnaker":0}},"boat_extra_spec":{"source":"manual","design":{"Mode":"semi","Stabilization":"finkeel","Hull":"mono"},"composition":{"BallastPercentage":0,"CfkPercentage":0,"AluPercentage":5,"GfkPercentage":78,"WoodPercentage":0,"EnginePercentage":1,"AmenityPercentage":0}},"boat_rating":{"version":"v0.0.1","lifter":0,"tcc":1,"speed_factor":0,"agility_factor":0,"stabilization_factor":0}},"sui_ecstasea":{"team":"","boat_info":{"source":"orc","name":"ECSTASEA","class":"ESSE 850","age":"2004","builder":"PROTEUS YACHTS","designer":"FELCI"},"boat_base_spec":{"source":"orc","dimension":{"length_over_all":8.5,"draft":1.999,"beam":2.19,"forestay_height":7.853,"wetted_surface_area":14.43,"displacement":1650,"crew_weight":300},"sail_area":{"main":28.06,"jib":17.44,"asymmetric_spinnaker":72.28,"symmetric_spinnaker":0}},"boat_extra_spec":{"source":"manual","design":{"Mode":"semi","Stabilization":"bulbkeel","Hull":"mono"},"composition":{"BallastPercentage":0,"CfkPercentage":1,"AluPercentage":3,"GfkPercentage":30,"WoodPercentage":0,"EnginePercentage":1,"AmenityPercentage":0}},"boat_rating":{"version":"v0.0.1","lifter":0,"tcc":1,"speed_factor":0,"agility_factor":0,"stabilization_factor":0}},"sui_example_gc32":{"team":"example","boat_info":{"source":"manual","name":"Example GC32","class":"GC32","age":"2012","builder":"Premier Composite Technologies","designer":"Dr Martin Fischer"},"boat_base_spec":{"source":"manual","dimension":{"length_over_all":10,"draft":2.1,"beam":6,"forestay_height":16.5,"wetted_surface_area":5,"displacement":975,"crew_weight":437.5},"sail_area":{"main":60,"jib":23.5,"asymmetric_spinnaker":90,"symmetric_spinnaker":0}},"boat_extra_spec":{"source":"manual","design":{"Mode":"hydrofoil","Stabilization":"foils","Hull":"multi"},"composition":{"BallastPercentage":0,"CfkPercentage":98,"AluPercentage":0,"GfkPercentage":0,"WoodPercentage":0,"EnginePercentage":0,"AmenityPercentage":0}},"boat_rating":{"version":"v0.0.1","lifter":0,"tcc":1,"speed_factor":0,"agility_factor":0,"stabilization_factor":0}},"sui_example_hobie":{"team":"example","boat_info":{"source":"manual","name":"Example Hobie","class":"Hobie Tiger 18","age":"1995","builder":"Hobie Cat Europe","designer":"Jacques Valer"},"boat_base_spec":{"source":"manual","dimension":{"length_over_all":5.51,"draft":0.71,"beam":2.6,"forestay_height":8.5,"wetted_surface_area":10,"displacement":180,"crew_weight":240},"sail_area":{"main":17,"jib":4.15,"asymmetric_spinnaker":0,"symmetric_spinnaker":21}},"boat_extra_spec":{"source":"manual","design":{"Mode":"semi","Stabilization":"daggerboard","Hull":"multi"},"composition":{"BallastPercentage":0,"CfkPercentage":0,"AluPercentage":10,"GfkPercentage":85,"WoodPercentage":0,"EnginePercentage":0,"AmenityPercentage":0}},"boat_rating":{"version":"v0.0.1","lifter":0,"tcc":1,"speed_factor":0,"agility_factor":0,"stabilization_factor":0}},"sui_fujin":{"team":"","boat_info":{"source":"orc","name":"FUJIN","class":"SWAN 55","age":"2022","builder":"NAUTOR SWAN","designer":"GERMAN FRERS"},"boat_base_spec":{"source":"orc","dimension":{"length_over_all":16.6,"draft":2.515,"beam":5.01,"forestay_height":15.89,"wetted_surface_area":62.62,"displacement":24633,"crew_weight":680},"sail_area":{"main":91.48,"jib":80.63,"asymmetric_spinnaker":0,"symmetric_spinnaker":0}},"boat_extra_spec":{"source":"manual","design":{"Mode":"displace","Stabilization":"finkeel","Hull":"mono"},"composition":{"BallastPercentage":0,"CfkPercentage":0,"AluPercentage":3,"GfkPercentage":40,"WoodPercentage":2,"EnginePercentage":3,"AmenityPercentage":15}},"boat_rating":{"version":"v0.0.1","lifter":0,"tcc":1,"speed_factor":0,"agility_factor":0,"stabilization_factor":0}},"sui_jay_jay":{"team":"","boat_info":{"source":"orc","name":"JAY  JAY","class":"J-70 ONE DESIGN","age":"2012","builder":"J BOATS","designer":"JOHNSTONE"},"boat_base_spec":{"source":"orc","dimension":{"length_over_all":6.942,"draft":1.45,"beam":2.26,"forestay_height":6.725,"wetted_surface_area":10.89,"displacement":1240,"crew_weight":340},"sail_area":{"main":16.12,"jib":10,"asymmetric_spinnaker":45.64,"symmetric_spinnaker":0}},"boat_extra_spec":{"source":"manual","design":{"Mode":"semi","Stabilization":"finkeel","Hull":"mono"},"composition":{"BallastPercentage":0,"CfkPercentage":3,"AluPercentage":0,"GfkPercentage":60,"WoodPercentage":0,"EnginePercentage":1,"AmenityPercentage":0}},"boat_rating":{"version":"v0.0.1","lifter":0,"tcc":1,"speed_factor":0,"agility_factor":0,"stabilization_factor":0}},"sui_noname":{"team":"","boat_info":{"source":"orc","name":"NONAME","class":"Dolphin 81","age":"1993","builder":"Maxi Dolphin","designer":"E.Santarelli"},"boat_base_spec":{"source":"orc","dimension":{"length_over_all":8.09,"draft":1.527,"beam":2.7,"forestay_height":7.66,"wetted_surface_area":13.13,"displacement":1507,"crew_weight":423},"sail_area":{"main":22.53,"jib":16.11,"asymmetric_spinnaker":0,"symmetric_spinnaker":58.5}},"boat_extra_spec":{"source":"manual","design":{"Mode":"semi","Stabilization":"finkeel","Hull":"mono"},"composition":{"BallastPercentage":0,"CfkPercentage":0,"AluPercentage":5,"GfkPercentage":78,"WoodPercentage":0,"EnginePercentage":1,"AmenityPercentage":0}},"boat_rating":{"version":"v0.0.1","lifter":0,"tcc":1,"speed_factor":0,"agility_factor":0,"stabilization_factor":0}}}